{"":"","code":"18","name_ko":"펜폴즈 토머스 하이랜드 쉬라즈","name_en":"Penfolds Thomas Hyland Shiraz","country":"호주","price":"80,000","awards":"160년 전통의 펜폴즈 와인을 현대적으로 재해석하여 세련되고 고급스러운 품질이 돋보이는 펜폴즈 대표 브랜드","Flavor":"토머스 하이랜드 range는 Dr. 펜폴즈의 사위이자 1800년대 부터 1914년 까지 펜폴즈 와인이 호주 No.1 와인이 될 수 있도록 기여한 토머스 하이랜드(Thomas Hyland)의 정신과 업적을 기리는 의미의 와인입니다. 토머스 하이랜드 와인은 맛과 구조감에 있어서 상대적으로 현대적 감각으로 재해석된 펜폴즈의 현대적인 버전이라 할 수 있습니다. 체리 쵸콜렛, 자두, 과일 케익 맛을 즐기실 수 있고, 오크 숙성 결과로 바닐라의 크리미한 질감, 부드러운 탄닌, 달콤한 맛이 매우 매력적인 레드 와인 입니다. 프렌치, 아메리칸 오크통에서 18개월간 숙성을 거칩니다. (뉴오크 비율 30%)"}
